waflibs/__init__.py
waflibs/arg_parse.py
waflibs/conf.py
waflibs/config.py
waflibs/database.py
waflibs/error.py
waflibs/filedir.py
waflibs/git.py
waflibs/log.py
waflibs/text.py
waflibs/uri.py
waflibs/utils.py
waflibs/dns/__init__.py
waflibs/dns/bind.py
waflibs/dns/mysql.py
waf_libs-2024.1.26.dist-info/LICENSE
waf_libs-2024.1.26.dist-info/METADATA
waf_libs-2024.1.26.dist-info/WHEEL
waf_libs-2024.1.26.dist-info/top_level.txt
waf_libs-2024.1.26.dist-info/RECORD
